main.py
trident_docker_cli-0.1.1.dist-info/METADATA
trident_docker_cli-0.1.1.dist-info/WHEEL
trident_docker_cli-0.1.1.dist-info/top_level.txt
trident_docker_cli-0.1.1.dist-info/RECORD
