Metadata-Version: 2.4
Name: trident-docker-cli
Version: 0.1.1
Summary: Add your description here
Requires-Python: >=3.12
Requires-Dist: docker>=7.1.0
Requires-Dist: pyyaml>=6.0.2
